mcp_server_docs/__init__.py
mcp_server_docs/__main__.py
mcp_server_docs/document_manager.py
mcp_server_docs/server.py
mcp_server_docs/scripts/__init__.py
mcp_server_docs/scripts/generate_metadata.py
mcp_server_docs/scripts/github_import.py
mcp_server_docs/scripts/url_import.py
docs_mcp-0.1.2.dist-info/METADATA
docs_mcp-0.1.2.dist-info/WHEEL
docs_mcp-0.1.2.dist-info/entry_points.txt
docs_mcp-0.1.2.dist-info/licenses/LICENSE
docs_mcp-0.1.2.dist-info/RECORD
