Metadata-Version: 2.4
Name: docs-mcp
Version: 0.1.2
Summary: An MCP server that enables efficient searching and referencing of user-configured documents
Project-URL: Homepage, https://github.com/herring101/docs-mcp
Project-URL: Repository, https://github.com/herring101/docs-mcp
Project-URL: Issues, https://github.com/herring101/docs-mcp/issues
Author: docs-mcp contributors
Maintainer: herring101
License: MIT
License-File: LICENSE
Keywords: documentation,embeddings,llm,mcp,search
Classifier: Development Status :: 4 - Beta
Classifier: Intended Audience :: Developers
Classifier: License :: OSI Approved :: MIT License
Classifier: Operating System :: OS Independent
Classifier: Programming Language :: Python :: 3
Classifier: Programming Language :: Python :: 3.12
Classifier: Topic :: Software Development :: Libraries :: Python Modules
Classifier: Topic :: Text Processing :: Indexing
Requires-Python: >=3.12
Requires-Dist: aiohttp>=3.9.0
Requires-Dist: beautifulsoup4>=4.12.0
Requires-Dist: markdownify>=0.11.0
Requires-Dist: mcp[cli]>=1.9.4
Requires-Dist: numpy>=2.3.0
Requires-Dist: openai>=1.86.0
Requires-Dist: pyyaml>=6.0.2
Requires-Dist: requests>=2.31.0
Requires-Dist: tqdm>=4.66.0
